README.md
pycrctrl.py
setup.cfg
setup.py
pycrctrl.egg-info/PKG-INFO
pycrctrl.egg-info/SOURCES.txt
pycrctrl.egg-info/dependency_links.txt
pycrctrl.egg-info/requires.txt
pycrctrl.egg-info/top_level.txt