Metadata-Version: 1.1
Name: pycrctrl
Version: 0.2
Summary: Controller for clonk's dedicated server
Home-page: https://github.com/Fulgen301/pycrctrl
Author: George Tokmaji
Author-email: tokmajigeorge@gmail.com
License: ISC
Download-URL: https://github.com/Fulgen301/pycrctrl/archive/0.2.tar.gz
Keywords: clonk,openclonk
Platform: UNKNOWN
